hyper_status/__init__.py
hyper_status/colors.py
hyper_status/status.py
hyper_status-1.3.dist-info/LICENSE
hyper_status-1.3.dist-info/METADATA
hyper_status-1.3.dist-info/WHEEL
hyper_status-1.3.dist-info/top_level.txt
hyper_status-1.3.dist-info/RECORD
