Metadata-Version: 2.1
Name: hyper-status
Version: 1.3
Summary: A status indicator that you can modify.
Home-page: https://github.com/Xithrius/hyper-status
Author: Xithrius
Author-email: xithrius@example.com
License: UNKNOWN
Platform: UNKNOWN
Classifier: Programming Language :: Python :: 3
Classifier: License :: OSI Approved :: MIT License
Classifier: Operating System :: OS Independent
Requires-Python: >=3.6
